README.rst
setup.py
django_events_watcher.egg-info/PKG-INFO
django_events_watcher.egg-info/SOURCES.txt
django_events_watcher.egg-info/dependency_links.txt
django_events_watcher.egg-info/not-zip-safe
django_events_watcher.egg-info/pbr.json
django_events_watcher.egg-info/top_level.txt
events_watcher/__init__.py
events_watcher/bridge.py
events_watcher/settings.py
events_watcher/utils.py
events_watcher/views.py
events_watcher/backends/__init__.py
events_watcher/backends/base.py
events_watcher/backends/database/__init__.py
events_watcher/backends/database/models.py
events_watcher/backends/database/south_migrations/0001_initial.py
events_watcher/backends/database/south_migrations/0002_auto__add_unique_event_object_id_name_content_type.py
events_watcher/backends/database/south_migrations/__init__.py
events_watcher/tests/__init__.py
events_watcher/tests/models.py
events_watcher/tests/settings.py
events_watcher/tests/tests.py