Metadata-Version: 1.1
Name: django-events-watcher
Version: 0.3.3
Summary: Events watcher is an event packaging library for Django to track changes made in your models.
Home-page: http://github.com/thoas/django-events-watcher
Author: Florent Messa
Author-email: florent.messa@gmail.com
License: UNKNOWN
Platform: UNKNOWN
Classifier: Environment :: Web Environment
Classifier: Intended Audience :: Developers
Classifier: License :: OSI Approved :: MIT License
Classifier: Operating System :: OS Independent
Classifier: Programming Language :: Python
Classifier: Programming Language :: Python :: 3
Classifier: Topic :: Utilities
